Famcy/__init__.py
Famcy/app.py
Famcy/famcy.ini
Famcy/wsgi.py
Famcy/_elements_/ELEMENT/ELEMENT.py
Famcy/_elements_/a/a.py
Famcy/_elements_/button/button.py
Famcy/_elements_/canvas/canvas.py
Famcy/_elements_/div/div.py
Famcy/_elements_/form/form.py
Famcy/_elements_/h1/h1.py
Famcy/_elements_/h2/h2.py
Famcy/_elements_/h3/h3.py
Famcy/_elements_/h4/h4.py
Famcy/_elements_/h5/h5.py
Famcy/_elements_/h6/h6.py
Famcy/_elements_/iframe/iframe.py
Famcy/_elements_/img/img.py
Famcy/_elements_/input/input.py
Famcy/_elements_/label/label.py
Famcy/_elements_/li/li.py
Famcy/_elements_/link/link.py
Famcy/_elements_/ol/ol.py
Famcy/_elements_/option/option.py
Famcy/_elements_/p/p.py
Famcy/_elements_/script/script.py
Famcy/_elements_/select/select.py
Famcy/_elements_/source/source.py
Famcy/_elements_/span/span.py
Famcy/_elements_/style/style.py
Famcy/_elements_/table/table.py
Famcy/_elements_/tbody/tbody.py
Famcy/_elements_/td/td.py
Famcy/_elements_/textarea/textarea.py
Famcy/_elements_/th/th.py
Famcy/_elements_/thead/thead.py
Famcy/_elements_/tr/tr.py
Famcy/_elements_/video/video.py
Famcy/_items_/__init__.py
Famcy/_items_/bar_chart/bar_chart.py
Famcy/_items_/display/__init__.py
Famcy/_items_/display/displayImage/displayImage.py
Famcy/_items_/display/displayLight/displayLight.py
Famcy/_items_/display/displayParagraph/displayParagraph.py
Famcy/_items_/display/displayPicWord/displayPicWord.py
Famcy/_items_/display/displayStepLoader/displayStepLoader.py
Famcy/_items_/display/displayTag/displayTag.py
Famcy/_items_/event_calendar/__init__.py
Famcy/_items_/event_calendar/event_calendar.py
Famcy/_items_/input_form/__init__.py
Famcy/_items_/input_form/input_form.py
Famcy/_items_/input_form/inputBlockSec/inputBlockSec.py
Famcy/_items_/input_form/inputBtn/inputBtn.py
Famcy/_items_/input_form/inputList/inputList.py
Famcy/_items_/input_form/inputParagraph/inputParagraph.py
Famcy/_items_/input_form/inputPassword/inputPassword.py
FamcyDev-0.3.63.dist-info/LICENSE
FamcyDev-0.3.63.dist-info/METADATA
FamcyDev-0.3.63.dist-info/WHEEL
FamcyDev-0.3.63.dist-info/top_level.txt
FamcyDev-0.3.63.dist-info/RECORD
