Metadata-Version: 2.1
Name: FamcyDev
Version: 0.3.63
Summary: Nexuni Co Ltd. Famcy management console framework
Home-page: https://github.com/nexuni/Famcy.git
Author: Nexuni Co Ltd. Develop Team
Author-email: developers@nexuni.com
License: Apache-2.0
Platform: UNKNOWN
Classifier: Intended Audience :: Developers
Classifier: License :: OSI Approved :: Apache Software License
Classifier: Programming Language :: Python :: 3.6
Classifier: Programming Language :: Python :: 3.7
Classifier: Operating System :: OS Independent
Classifier: Topic :: Software Development :: Libraries
Requires-Python: >=3.6
Requires-Dist: flask
Requires-Dist: flask-login
Requires-Dist: flask-sijax
Requires-Dist: flask-sse
Requires-Dist: gadgethiServerUtils (==999.999)
Requires-Dist: markdown
Requires-Dist: redis (==4.1.0)
Requires-Dist: flask-kvsession (==0.6.2)
Requires-Dist: dill
Requires-Dist: plotly
